interdim/__init__.py
interdim/cluster.py
interdim/pipeline.py
interdim/reduce.py
interdim/score.py
interdim/vis.py
interdim-1.0.2.dist-info/LICENSE
interdim-1.0.2.dist-info/METADATA
interdim-1.0.2.dist-info/WHEEL
interdim-1.0.2.dist-info/top_level.txt
interdim-1.0.2.dist-info/RECORD
