Metadata-Version: 2.1
Name: interdim
Version: 1.0.2
Summary: Interactive Dimensionality Reduction, Clustering, and Visualization
Author-email: Matthew Shinkle <matthewshinkle@gmail.com>
License: BSD-3-Clause
Project-URL: Homepage, https://github.com/MShinkle/interdim
Project-URL: Bug Tracker, https://github.com/MShinkle/interdim/issues
Keywords: dimensionality reduction,clustering,visualization,machine learning,data analysis
Classifier: Programming Language :: Python :: 3
Classifier: Programming Language :: Python :: 3.8
Classifier: Programming Language :: Python :: 3 :: Only
Classifier: License :: OSI Approved :: BSD License
Classifier: Operating System :: OS Independent
Classifier: Intended Audience :: Science/Research
Classifier: Topic :: Scientific/Engineering :: Visualization
Classifier: Topic :: Scientific/Engineering :: Artificial Intelligence
Requires-Python: >=3.8
License-File: LICENSE
Requires-Dist: numpy
Requires-Dist: scikit-learn
Requires-Dist: plotly
Requires-Dist: dash
Provides-Extra: all
Requires-Dist: umap-learn; extra == "all"
Requires-Dist: hdbscan; extra == "all"
Provides-Extra: hdbscan
Requires-Dist: hdbscan; extra == "hdbscan"
Provides-Extra: test
Requires-Dist: pytest; extra == "test"
Provides-Extra: umap
Requires-Dist: umap-learn; extra == "umap"
